setup.cfg
setup.py
src/browse/__init__.py
src/browse/browser.py
src/browse.egg-info/PKG-INFO
src/browse.egg-info/SOURCES.txt
src/browse.egg-info/dependency_links.txt
src/browse.egg-info/entry_points.txt
src/browse.egg-info/top_level.txt
test/test_browse.py