Metadata-Version: 1.1
Name: browse
Version: 1.0.0
Summary: Open a web page in a browser, as simple as that...
Home-page: http://packages.python.org/browse
Author: Thomas Cokelaer
Author-email: cokelaer@gmail.com
License: LGPL
Platform: Linux
Classifier: Development Status :: 6 - Mature
Classifier: Environment :: Console
Classifier: Intended Audience :: Developers
Classifier: Intended Audience :: Education
Classifier: Intended Audience :: Science/Research
Classifier: License :: OSI Approved :: GNU General Public License v3 (GPLv3)
Classifier: Operating System :: OS Independent
Classifier: Programming Language :: Python :: 2.7
Classifier: Topic :: Scientific/Engineering
